DigitalCellSorter/Combat.py
DigitalCellSorter/FastTSNE.py
DigitalCellSorter/GeneNameConverter.py
DigitalCellSorter/GenericFunctions.py
DigitalCellSorter/MakeMarkerDict.py
DigitalCellSorter/ReadPrepareDataHCA.py
DigitalCellSorter/ReadPrepareDataHCApreviewDataset.py
DigitalCellSorter/VisualizationFunctions.py
DigitalCellSorter/__init__.py
DigitalCellSorter/__main__.py
DigitalCellSorter/core.py
DigitalCellSorter/ensembl_hugo_entrez_alias_dict_Human.pklz
DigitalCellSorter/ensembl_hugo_entrez_alias_dict_Mouse.pklz
DigitalCellSorter/fromFunctools.py
DigitalCellSorter/__pycache__/Combat.cpython-37.pyc
DigitalCellSorter/__pycache__/Combat.cpython-38.pyc
DigitalCellSorter/__pycache__/DigitalCellSorter.cpython-36.pyc
DigitalCellSorter/__pycache__/DigitalCellSorter.cpython-37.pyc
DigitalCellSorter/__pycache__/FastTSNE.cpython-37.pyc
DigitalCellSorter/__pycache__/FastTSNE.cpython-38.pyc
DigitalCellSorter/__pycache__/GeneNameConverter.cpython-37.pyc
DigitalCellSorter/__pycache__/GeneNameConverter.cpython-38.pyc
DigitalCellSorter/__pycache__/GenericFunctions.cpython-37.pyc
DigitalCellSorter/__pycache__/GenericFunctions.cpython-38.pyc
DigitalCellSorter/__pycache__/MakeMarkerDict.cpython-37.pyc
DigitalCellSorter/__pycache__/ReadPrepareDataHCA.cpython-37.pyc
DigitalCellSorter/__pycache__/ReadPrepareDataHCA.cpython-38.pyc
DigitalCellSorter/__pycache__/ReadPrepareDataHCApreviewDataset.cpython-36.pyc
DigitalCellSorter/__pycache__/ReadPrepareDataHCApreviewDataset.cpython-37.pyc
DigitalCellSorter/__pycache__/VisualizationFunctions.cpython-37.pyc
DigitalCellSorter/__pycache__/VisualizationFunctions.cpython-38.pyc
DigitalCellSorter/__pycache__/__init__.cpython-36.pyc
DigitalCellSorter/__pycache__/__init__.cpython-37.pyc
DigitalCellSorter/__pycache__/__init__.cpython-38.pyc
DigitalCellSorter/__pycache__/__main__.cpython-38.pyc
DigitalCellSorter/__pycache__/core.cpython-37.pyc
DigitalCellSorter/__pycache__/core.cpython-38.pyc
DigitalCellSorter/__pycache__/generalForGeneLists.cpython-36.pyc
DigitalCellSorter-1.3.7.6.dist-info/LICENSE
DigitalCellSorter-1.3.7.6.dist-info/METADATA
DigitalCellSorter-1.3.7.6.dist-info/WHEEL
DigitalCellSorter-1.3.7.6.dist-info/top_level.txt
DigitalCellSorter-1.3.7.6.dist-info/RECORD
