Metadata-Version: 2.1
Name: DigitalCellSorter
Version: 1.3.7.6
Summary: Toolkit for analysis and identification of cell types from heterogeneous single cell RNA-seq data
Home-page: https://github.com/sdomanskyi/DigitalCellSorter
Author: S. Domanskyi, A. Szedlak, N. T Hawkins, J. Wang, T. Bertus, A. Hakansson, G. Paternostro, C. Piermarocchi
Author-email: s.domanskyi@gmail.com
License: MIT License
Download-URL: https://github.com/sdomanskyi/DigitalCellSorter/archive/1.3.7.tar.gz
Keywords: single cell RNA sequencing,cell type identification,biomarkers
Platform: UNKNOWN
Classifier: License :: OSI Approved :: MIT License
Classifier: Programming Language :: Python :: 3
Classifier: Topic :: Scientific/Engineering :: Bio-Informatics
Classifier: Intended Audience :: Science/Research
Classifier: Intended Audience :: Education
Classifier: Intended Audience :: Developers
Classifier: Intended Audience :: End Users/Desktop
Classifier: Operating System :: MacOS
Classifier: Operating System :: Microsoft :: Windows
Classifier: Operating System :: Unix
Classifier: Topic :: Education
Classifier: Topic :: Utilities
Requires-Python: >=3
Requires-Dist: numpy (>=1.16.4)
Requires-Dist: pandas (>=0.24.2)
Requires-Dist: patsy (>=0.5.1)
Requires-Dist: xlrd (>=1.2.0)
Requires-Dist: openpyxl (>=3.0.3)
Requires-Dist: tables (>=3.5.1)
Requires-Dist: scipy (>=1.3.0)
Requires-Dist: matplotlib (>=3.1.0)
Requires-Dist: scikit-learn (>=0.21.2)
Requires-Dist: mygene (>=3.1.0)
Requires-Dist: plotly (>=4.1.1)
Requires-Dist: adjustText (>=0.7.3)
